range_announcer/__init__.py
range_announcer/__main__.py
range_announcer/announcer.py
range_announcer/rangeannouncer.json
range_announcer/sunrise.py
range_announcer/switch.py
range_announcer/timezone.py
range_announcer/sound/15_minutes.mp3
range_announcer/sound/30_minutes.mp3
range_announcer/sound/5_minutes.mp3
range_announcer/sound/BackInBlack.mp3
range_announcer/sound/closed.mp3
range_announcer/sound/complete.wav
range_announcer/sound/one_hour.mp3
range_announcer/sound/playsound.py
range_announcer-1.3.2.dist-info/licenses/LICENSE
range_announcer-1.3.2.dist-info/METADATA
range_announcer-1.3.2.dist-info/WHEEL
range_announcer-1.3.2.dist-info/entry_points.txt
range_announcer-1.3.2.dist-info/top_level.txt
range_announcer-1.3.2.dist-info/RECORD
