Metadata-Version: 2.4
Name: Range_Announcer
Version: 1.3.2
Summary: Announce range closure as sunset approaches
Home-page: https://github.com/CrazyVikingProductions/range_announcer
Author: Michael J. Swenson
Author-email: mikswenson@gmail.com
Project-URL: Bug Reports, https://github.com/CrazyVikingProductions/range_announcer/issues
Project-URL: Source, https://github.com/CrazyVikingProductions/range_announcer
Keywords: sunset closure announce
Classifier: Development Status :: 5 - Production/Stable
Classifier: Environment :: Console
Classifier: Natural Language :: English
Classifier: Operating System :: OS Independent
Classifier: Intended Audience :: Other Audience
Classifier: Topic :: Other/Nonlisted Topic
Classifier: License :: OSI Approved :: BSD License
Classifier: Programming Language :: Python
Classifier: Programming Language :: Python :: 3
Classifier: Programming Language :: Python :: 3.6
Classifier: Programming Language :: Python :: 3.7
Classifier: Programming Language :: Python :: 3.8
Classifier: Programming Language :: Python :: 3 :: Only
Classifier: Programming Language :: Python :: Implementation :: CPython
License-File: LICENSE
Requires-Dist: pygame>=2.1
Requires-Dist: requests
Dynamic: license-file
